README
setup.cfg
setup.py
fortune/__init__.py
sv_fortune.egg-info/PKG-INFO
sv_fortune.egg-info/SOURCES.txt
sv_fortune.egg-info/dependency_links.txt
sv_fortune.egg-info/entry_points.txt
sv_fortune.egg-info/top_level.txt