Metadata-Version: 1.1
Name: sv-fortune
Version: 1.1
Summary: Python version of old BSD Unix fortune program, python3-patched
Home-page: http://software.clapper.org/fortune/
Author: Brian M. Clapper
Author-email: bmc@clapper.org
License: BSD-style license
Download-URL: http://pypi.python.org/packages/source/f/sv_fortune/sv_fortune-1.1.tar.gz
Platform: UNKNOWN
Classifier: Intended Audience :: End Users/Desktop
Classifier: Operating System :: OS Independent
Classifier: Topic :: Games/Entertainment
Classifier: License :: OSI Approved :: BSD License
Classifier: Programming Language :: Python :: 2
Classifier: Programming Language :: Python :: 3
Classifier: Topic :: Text Processing :: Filters
